{"nodes": [{"id": "backend_app_api_stream_py", "label": "stream.py", "file_type": "code", "source_file": "backend\\app\\api\\stream.py", "source_location": "L1"}, {"id": "stream_stream_status", "label": "stream_status()", "file_type": "code", "source_file": "backend\\app\\api\\stream.py", "source_location": "L12"}, {"id": "stream_stream_start", "label": "stream_start()", "file_type": "code", "source_file": "backend\\app\\api\\stream.py", "source_location": "L18"}, {"id": "stream_stream_stop", "label": "stream_stop()", "file_type": "code", "source_file": "backend\\app\\api\\stream.py", "source_location": "L24"}, {"id": "stream_rationale_1", "label": "Streaming API endpoints.", "file_type": "rationale", "source_file": "backend\\app\\api\\stream.py", "source_location": "L1"}], "edges": [{"source": "backend_app_api_stream_py", "target": "fastapi", "relation": "imports_from", "confidence": "EXTRACTED", "source_file": "backend\\app\\api\\stream.py", "source_location": "L4", "weight": 1.0}, {"source": "backend_app_api_stream_py", "target": "app_api_deps", "relation": "imports_from", "confidence": "EXTRACTED", "source_file": "backend\\app\\api\\stream.py", "source_location": "L6", "weight": 1.0}, {"source": "backend_app_api_stream_py", "target": "stream_stream_status", "relation": "contains", "confidence": "EXTRACTED", "source_file": "backend\\app\\api\\stream.py", "source_location": "L12", "weight": 1.0}, {"source": "backend_app_api_stream_py", "target": "stream_stream_start", "relation": "contains", "confidence": "EXTRACTED", "source_file": "backend\\app\\api\\stream.py", "source_location": "L18", "weight": 1.0}, {"source": "backend_app_api_stream_py", "target": "stream_stream_stop", "relation": "contains", "confidence": "EXTRACTED", "source_file": "backend\\app\\api\\stream.py", "source_location": "L24", "weight": 1.0}, {"source": "stream_rationale_1", "target": "backend_app_api_stream_py", "relation": "rationale_for", "confidence": "EXTRACTED", "source_file": "backend\\app\\api\\stream.py", "source_location": "L1", "weight": 1.0}]}